requests_rust-0.1.3.dist-info/METADATA
requests_rust-0.1.3.dist-info/WHEEL
requests_rust-0.1.3.dist-info/license_files/LICENSE
requests_rust/__init__.py
requests_rust/requests_rust.cp312-win32.pyd
requests_rust-0.1.3.dist-info/RECORD
