Metadata-Version: 2.3
Name: requests_rust
Version: 0.1.3
Classifier: Programming Language :: Rust
Classifier: Programming Language :: Python :: Implementation :: CPython
Classifier: Programming Language :: Python :: Implementation :: PyPy
License-File: LICENSE
Summary: A simple HTTP/S client for Python written in rust
Author-email: Hamid <hamid@darabi.website>
Requires-Python: >=3.10
Project-URL: Homepage, https://github.com/H4mid2019/requests_rust
Project-URL: Issues, https://github.com/H4mid2019/requests_rust/issues
